{
"type": "FeatureCollection",
"name": "geo_18_介護医療院",
"crs": { "type": "name", "properties": { "name": "urn:ogc:def:crs:OGC:1.3:CRS84" } },
"features": [
{ "type": "Feature", "properties": { "内容": "福井リハビリテーション病院介護医療院【介護医療院】福井市南楢原町20字大畑2番地", "url": "https://www.kaigokensaku.mhlw.go.jp/18/index.php?action_kouhyou_detail_004_kani=true&JigyosyoCd=18B0100012-00&ServiceCd=550&Type=search", "url2": "http://www.otaki-hp.or.jp/group/fukui-rehabilitation/" }, "geometry": { "type": "Point", "coordinates": [ 136.179879699999987, 36.0978243 ] } },
{ "type": "Feature", "properties": { "内容": "介護医療院まこと【介護医療院】福井県福井市板垣５丁目201", "url": "https://www.kaigokensaku.mhlw.go.jp/18/index.php?action_kouhyou_detail_004_kani=true&JigyosyoCd=18B0100038-00&ServiceCd=550&Type=search", "url2": "hikaricare@hikarigroup.jp" }, "geometry": { "type": "Point", "coordinates": [ 136.2280151, 36.0441294 ] } },
{ "type": "Feature", "properties": { "内容": "田中病院　介護医療院【介護医療院】福井県小浜市遠敷10丁目601番地の1", "url": "https://www.kaigokensaku.mhlw.go.jp/18/index.php?action_kouhyou_detail_004_kani=true&JigyosyoCd=18B0400016-00&ServiceCd=550&Type=search", "url2": "https://sites.google.com/view/tanakahospital-obama/" }, "geometry": { "type": "Point", "coordinates": [ 135.774889977909879, 35.485256400000019 ] } },
{ "type": "Feature", "properties": { "内容": "介護医療院　キラキラの家【介護医療院】要町1-13", "url": "https://www.kaigokensaku.mhlw.go.jp/18/index.php?action_kouhyou_detail_004_kani=true&JigyosyoCd=18B0500021-00&ServiceCd=550&Type=search", "url2": null }, "geometry": { "type": "Point", "coordinates": [ 139.6995197, 35.7343722 ] } },
{ "type": "Feature", "properties": { "内容": "介護医療院あかり【介護医療院】福井県大野市明倫町11-2尾崎病院", "url": "https://www.kaigokensaku.mhlw.go.jp/18/index.php?action_kouhyou_detail_004_kani=true&JigyosyoCd=18B0500013-00&ServiceCd=550&Type=search", "url2": "https://sites.google.com/view/ozaki-hp/" }, "geometry": { "type": "Point", "coordinates": [ 136.490674, 35.9825724 ] } },
{ "type": "Feature", "properties": { "内容": "介護医療院　かがやき【介護医療院】福井県鯖江市旭町4丁目9番10号", "url": "https://www.kaigokensaku.mhlw.go.jp/18/index.php?action_kouhyou_detail_004_kani=true&JigyosyoCd=18B0700019-00&ServiceCd=550&Type=search", "url2": "https://www.jujinkai.or.jp/" }, "geometry": { "type": "Point", "coordinates": [ 136.188240600000029, 35.950147500000014 ] } },
{ "type": "Feature", "properties": { "内容": "広瀬病院介護医療院サンク【介護医療院】福井県鯖江市旭町1-2-8", "url": "https://www.kaigokensaku.mhlw.go.jp/18/index.php?action_kouhyou_detail_004_kani=true&JigyosyoCd=18B0700035-00&ServiceCd=550&Type=search", "url2": "https://www.hirosebyouin.com" }, "geometry": { "type": "Point", "coordinates": [ 136.1873295, 35.9438976 ] } },
{ "type": "Feature", "properties": { "内容": "谷川病院介護医療院【介護医療院】本町4丁目3番14号", "url": "https://www.kaigokensaku.mhlw.go.jp/18/index.php?action_kouhyou_detail_004_kani=true&JigyosyoCd=18B0700027-00&ServiceCd=550&Type=search", "url2": null }, "geometry": { "type": "Point", "coordinates": [ 136.184920647156019, 35.949891090971832 ] } },
{ "type": "Feature", "properties": { "内容": "笠原病院　介護医療院【介護医療院】福井県越前市塚町２１４番地", "url": "https://www.kaigokensaku.mhlw.go.jp/18/index.php?action_kouhyou_detail_004_kani=true&JigyosyoCd=18B0300026-00&ServiceCd=550&Type=search", "url2": "http://www.kasahara-hosp.or.jp" }, "geometry": { "type": "Point", "coordinates": [ 136.1687173, 35.9034961 ] } },
{ "type": "Feature", "properties": { "内容": "介護医療院　今立中央病院【介護医療院】福井県越前市粟田部町33-1一般財団法人　今立中央病院内　併設", "url": "https://www.kaigokensaku.mhlw.go.jp/18/index.php?action_kouhyou_detail_004_kani=true&JigyosyoCd=18B0300018-00&ServiceCd=550&Type=search", "url2": "https://www.imadatechuo-hp.com" }, "geometry": { "type": "Point", "coordinates": [ 136.244086, 35.9171079 ] } }
]
}
