{
"type": "FeatureCollection",
"name": "geo_18_短期入所療養介護(療養病床を有する病院等）",
"crs": { "type": "name", "properties": { "name": "urn:ogc:def:crs:OGC:1.3:CRS84" } },
"features": [
{ "type": "Feature", "properties": { "内容": "さくら病院【短期入所療養介護(療養病床を有する病院等）】福井県福井市下荒井町第21号44番地の1さくら病院", "url": "https://www.kaigokensaku.mhlw.go.jp/18/index.php?action_kouhyou_detail_004_kani=true&JigyosyoCd=1870103247-00&ServiceCd=&Type=search", "url2": "http://www.senjukai.com" }, "geometry": { "type": "Point", "coordinates": [ 136.208969, 36.024989 ] } },
{ "type": "Feature", "properties": { "内容": "ひらい内科消化器科医院短期入所療養介護施設【短期入所療養介護(療養病床を有する病院等）】福井市渕4丁目1813", "url": "https://www.kaigokensaku.mhlw.go.jp/18/index.php?action_kouhyou_detail_004_kani=true&JigyosyoCd=1810119907-00&ServiceCd=&Type=search", "url2": "http://www.hirainaikashoukakika.org/" }, "geometry": { "type": "Point", "coordinates": [ 136.182073, 36.0455021 ] } },
{ "type": "Feature", "properties": { "内容": "池端病院【短期入所療養介護(療養病床を有する病院等）】福井県越前市今宿町８－１", "url": "https://www.kaigokensaku.mhlw.go.jp/18/index.php?action_kouhyou_detail_004_kani=true&JigyosyoCd=1810314557-00&ServiceCd=&Type=search", "url2": "http://www.ikebata.jp" }, "geometry": { "type": "Point", "coordinates": [ 136.169917100000021, 35.8654366 ] } },
{ "type": "Feature", "properties": { "内容": "宮崎病院【短期入所療養介護(療養病床を有する病院等）】坂井市三国町北本町2-2-6", "url": "https://www.kaigokensaku.mhlw.go.jp/18/index.php?action_kouhyou_detail_004_kani=true&JigyosyoCd=1811715133-00&ServiceCd=&Type=search", "url2": "http://www.miyazaki-hp.com" }, "geometry": { "type": "Point", "coordinates": [ 136.149079300000039, 36.2163367 ] } },
{ "type": "Feature", "properties": { "内容": "若狭町国民健康保険上中病院【短期入所療養介護(療養病床を有する病院等）】福井県三方上中郡若狭町市場第１９号５番地", "url": "https://www.kaigokensaku.mhlw.go.jp/18/index.php?action_kouhyou_detail_004_kani=true&JigyosyoCd=1812410056-00&ServiceCd=&Type=search", "url2": "http://www.town.fukui-wakasa.lg.jp/town/category/page.asp?Page=34" }, "geometry": { "type": "Point", "coordinates": [ 135.85788320000006, 35.4618018 ] } }
]
}
