{
"type": "FeatureCollection",
"name": "geo_18_短期入所療養介護（介護医療院）",
"crs": { "type": "name", "properties": { "name": "urn:ogc:def:crs:OGC:1.3:CRS84" } },
"features": [
{ "type": "Feature", "properties": { "内容": "いわき医院介護医療院【短期入所療養介護（介護医療院）】福井県福井市三十八社町10-8", "url": "https://www.kaigokensaku.mhlw.go.jp/18/index.php?action_kouhyou_detail_004_kani=true&JigyosyoCd=18B0100020-00&ServiceCd=551&Type=search", "url2": null }, "geometry": { "type": "Point", "coordinates": [ 136.19385170000001, 35.9968944 ] } },
{ "type": "Feature", "properties": { "内容": "介護医療院　今立中央病院【短期入所療養介護（介護医療院）】福井県越前市粟田部町33-1一般財団法人　今立中央病院内　併設", "url": "https://www.kaigokensaku.mhlw.go.jp/18/index.php?action_kouhyou_detail_004_kani=true&JigyosyoCd=18B0300018-00&ServiceCd=551&Type=search", "url2": "https://www.imadatechuo-hp.com" }, "geometry": { "type": "Point", "coordinates": [ 136.244086, 35.9171079 ] } },
{ "type": "Feature", "properties": { "内容": "医療法人　笠原病院【短期入所療養介護（介護医療院）】福井県越前市塚町２１４番地", "url": "https://www.kaigokensaku.mhlw.go.jp/18/index.php?action_kouhyou_detail_004_kani=true&JigyosyoCd=18B0300026-00&ServiceCd=551&Type=search", "url2": "http://www.kasahara-hosp.or.jp" }, "geometry": { "type": "Point", "coordinates": [ 136.1687173, 35.9034961 ] } }
]
}
